{
    "@class": "com.kony.gen.viz.model.container.KVizScrollFlexForm",
    "DNDConfig": null,
    "_margin_": [
        0,
        0,
        0,
        0
    ],
    "_orientation_": 1,
    "_padding_": [
        0,
        0,
        0,
        0
    ],
    "_percent_": true,
    "_skin_": "s8f0c903d1ce4688a86923ffe27657ee",
    "_title_": null,
    "addWidgetsdone": false,
    "allboxes": [],
    "canUpdateUI": true,
    "children": [
        "CopyflxMainbrnachlist1"
    ],
    "containerId": true,
    "containerweight": 100,
    "currentLocale": "default",
    "device": "iPhone14",
    "displayorientation": 3,
    "enabledforidletimeout": false,
    "id": "CopySegBranchList1",
    "info": null,
    "initdone": false,
    "inputaccessoryviewtype": 4,
    "intransitionconfig": {
        "formTransition": "None"
    },
    "iscustomlayout": false,
    "isvisible": true,
    "kuid": "b6d81a3593be4fd0852a2642a2ee440a",
    "name": "kony.ui.Form2",
    "needappmenu": true,
    "outtransitionconfig": {
        "formTransition": "None"
    },
    "paddinginpixel": false,
    "platform": "iphone",
    "prevDevice": "iPhone14",
    "prevPlatform": "iphone",
    "retaincontentalignment": false,
    "retainflexpositionproperties": false,
    "retainscrollposition": false,
    "titlebar": true,
    "type": 3,
    "wType": "Form"
}