{
    "DNDConfig": null,
    "_height_": {
        "type": "string",
        "value": "82%"
    },
    "_left_": {
        "type": "string",
        "value": "0"
    },
    "_margin_": [
        0,
        0,
        0,
        0
    ],
    "_orientation_": 6,
    "_padding_": [
        0,
        0,
        0,
        0
    ],
    "_percent_": true,
    "_skin_": "sc7ecba7165e4c97b39d5cb9b3bd5145",
    "_top_": {
        "type": "string",
        "value": "8%"
    },
    "_width_": {
        "type": "string",
        "value": "100%"
    },
    "allboxes": [],
    "allowhorizontalbounce": false,
    "allowverticalbounce": false,
    "bounces": true,
    "canUpdateUI": true,
    "children": [
        "flxBody"
    ],
    "clipbounds": true,
    "containerweight": 100,
    "decelerat": false,
    "dragg": false,
    "enablescrolling": true,
    "horizontalscrollindicator": true,
    "id": "flxScrollBody",
    "info": null,
    "iscustomlayout": false,
    "isvisible": true,
    "kuid": "eb0f2ed0ee414c78ad07b9ef62e225ff",
    "layouttype": 2,
    "name": "kony.ui.FlexScrollContainer",
    "pagingenabled": false,
    "parent": "flxMain",
    "pf": "frmDashBoard",
    "retaincontentalignment": false,
    "retainflexpositionproperties": false,
    "retainflowhorizontalalignment": false,
    "scrolldirection": 2,
    "snapgridsize": 10,
    "snaptogrid": true,
    "track": false,
    "verticalscrollindicator": true,
    "wType": "FlexScrollContainer",
    "widgetalignment": 1,
    "zindex": 4
}