{
    "DNDConfig": null,
    "_height_": {
        "type": "string",
        "value": "55dp"
    },
    "_left_": {
        "type": "string",
        "value": "5%"
    },
    "_margin_": [
        0,
        0,
        0,
        0
    ],
    "_orientation_": 6,
    "_padding_": [
        0,
        0,
        0,
        0
    ],
    "_percent_": true,
    "_skin_": "s723c97c61a94699b97eaaf1911071a6",
    "_top_": {
        "type": "string",
        "value": "10dp"
    },
    "_width_": {
        "type": "string",
        "value": "94%"
    },
    "allboxes": [],
    "autogrowmode": 0,
    "canUpdateUI": true,
    "centerx": {
        "type": "string",
        "value": "50%"
    },
    "centery": {
        "type": "string",
        "value": "50%"
    },
    "children": [
        "flxEmailLabel",
        "flxTextboxEmail"
    ],
    "clipbounds": false,
    "containerweight": 100,
    "enablescrolling": true,
    "id": "flxEmail",
    "info": null,
    "iscustomlayout": false,
    "isvisible": true,
    "kuid": "ga2431bc3c614372a104b1f02fc9d78e",
    "layouttype": 2,
    "name": "kony.ui.FlexContainer",
    "parent": "flxEmailContainer",
    "pf": "frmProfile",
    "retaincontentalignment": false,
    "retainflexpositionproperties": false,
    "retainflowhorizontalalignment": false,
    "snapgridsize": 10,
    "snaptogrid": true,
    "wType": "FlexContainer",
    "widgetalignment": 1
}