{
    "DNDConfig": null,
    "_height_": {
        "type": "string",
        "value": "500dp"
    },
    "_left_": {
        "type": "string",
        "value": "3dp"
    },
    "_margin_": [
        0,
        0,
        0,
        0
    ],
    "_orientation_": 6,
    "_padding_": [
        0,
        0,
        0,
        0
    ],
    "_percent_": true,
    "_skin_": "s99223cb09774b53ab8fa826ac58f9b6",
    "_top_": {
        "type": "string",
        "value": "0dp"
    },
    "_width_": {
        "type": "string",
        "value": "100%"
    },
    "actionsInfo": {},
    "allboxes": [],
    "autogrowmode": 0,
    "canUpdateUI": true,
    "centery": {
        "type": "string",
        "value": "51.99%"
    },
    "children": [
        "imgLogin",
        "btnLOGIN"
    ],
    "clipbounds": false,
    "containerweight": 100,
    "enablescrolling": true,
    "id": "flexlogin",
    "info": null,
    "iscustomlayout": false,
    "isvisible": true,
    "kuid": "ia5931b389d4450d80e143af09b0962a",
    "layouttype": 4,
    "name": "kony.ui.FlexContainer",
    "parent": "Form1",
    "pf": "Form1",
    "retaincontentalignment": false,
    "retainflexpositionproperties": false,
    "retainflowhorizontalalignment": false,
    "snapgridsize": 10,
    "snaptogrid": true,
    "wType": "FlexContainer",
    "widgetalignment": 1,
    "zindex": 1
}