{
    "@class": "com.kony.gen.viz.model.component.KVizCamera",
    "DNDConfig": null,
    "_bottom_": {
        "type": "number",
        "value": "10"
    },
    "_height_": {
        "type": "string",
        "value": "30%"
    },
    "_margin_": [
        0,
        0,
        0,
        0
    ],
    "_padding_": [
        0,
        0,
        0,
        0
    ],
    "_skin_": "sb6fec46a3434ff6873e7de59bd66fa1",
    "_text_": "TAKE A PHOTO",
    "_width_": {
        "type": "string",
        "value": "80%"
    },
    "androidwearos": {
        "render": false
    },
    "canUpdateUI": true,
    "centerx": {
        "type": "string",
        "value": "50%"
    },
    "containerweight": 100,
    "contentalignment": 5,
    "desktopweb": {
        "psp": {
            "poster": "cameraicon.png"
        }
    },
    "id": "cam",
    "info": null,
    "iscustomlayout": false,
    "isvisible": true,
    "kuid": "ff2224fc2d9a4c4b8ee4503b18f15564",
    "name": "kony.ui.Camera",
    "parent": "flxTakeAaPhoto",
    "pf": "frmRegister2",
    "retaincontentalignment": false,
    "retainflexpositionproperties": false,
    "spaan": {
        "render": false
    },
    "spaandroidtablet": {
        "render": false
    },
    "spaip": {
        "render": false
    },
    "spaipad": {
        "render": false
    },
    "spawindowstablet": {
        "render": false
    },
    "spawinphone8": {
        "render": false
    },
    "wType": "Camera",
    "watchos": {
        "render": false
    },
    "zindex": 1
}