[ {
  "name" : "activity_by",
  "sourceFieldname" : "activity_by",
  "description" : "activity_by",
  "dataType" : "string",
  "hasIndex" : false,
  "unique" : false,
  "primarykey" : false,
  "namefield" : false,
  "nullable" : true,
  "custom" : false,
  "createable" : true,
  "updateable" : true,
  "audit" : false,
  "customizable" : false,
  "fieldLength" : 36,
  "precision" : 0,
  "fieldOrder" : 0,
  "fieldProperties" : {
    "autoGenerated" : "false"
  },
  "etag" : "11dacd9d-bf42-43cd-a05c-2c49ee60866a",
  "isExtended" : false
}, {
  "name" : "activity_on",
  "sourceFieldname" : "activity_on",
  "description" : "activity_on",
  "dataType" : "date",
  "hasIndex" : false,
  "unique" : false,
  "primarykey" : false,
  "namefield" : false,
  "nullable" : true,
  "custom" : false,
  "createable" : true,
  "updateable" : true,
  "audit" : false,
  "customizable" : false,
  "fieldLength" : 23,
  "precision" : 0,
  "fieldOrder" : 0,
  "fieldProperties" : {
    "autoGenerated" : "false"
  },
  "etag" : "3e9e758f-51c5-469f-81c8-9297a34a0b25",
  "isExtended" : false
}, {
  "name" : "activity_ref_id",
  "sourceFieldname" : "activity_ref_id",
  "description" : "activity_ref_id",
  "dataType" : "string",
  "hasIndex" : false,
  "unique" : false,
  "primarykey" : false,
  "namefield" : false,
  "nullable" : true,
  "custom" : false,
  "createable" : true,
  "updateable" : true,
  "audit" : false,
  "customizable" : false,
  "fieldLength" : 50,
  "precision" : 0,
  "fieldOrder" : 0,
  "fieldProperties" : {
    "autoGenerated" : "false"
  },
  "etag" : "b929151a-16b3-4f81-b824-c53b35fbee44",
  "isExtended" : false
}, {
  "name" : "activity_type",
  "sourceFieldname" : "activity_type",
  "description" : "activity_type",
  "dataType" : "string",
  "hasIndex" : false,
  "unique" : false,
  "primarykey" : false,
  "namefield" : false,
  "nullable" : true,
  "custom" : false,
  "createable" : true,
  "updateable" : true,
  "audit" : false,
  "customizable" : false,
  "fieldLength" : 40,
  "precision" : 0,
  "fieldOrder" : 0,
  "fieldProperties" : {
    "autoGenerated" : "false"
  },
  "etag" : "b9983e0e-ae71-4542-b3bd-9a32aba2d7f3",
  "isExtended" : false
}, {
  "name" : "asset_id",
  "sourceFieldname" : "asset_id",
  "description" : "asset_id",
  "dataType" : "string",
  "hasIndex" : false,
  "unique" : false,
  "primarykey" : false,
  "namefield" : false,
  "nullable" : true,
  "custom" : false,
  "createable" : true,
  "updateable" : true,
  "audit" : false,
  "customizable" : false,
  "fieldLength" : 100,
  "precision" : 0,
  "fieldOrder" : 0,
  "fieldProperties" : {
    "autoGenerated" : "false"
  },
  "etag" : "6bb3eefd-e34b-4067-96de-3be820692433",
  "isExtended" : false
}, {
  "name" : "browser",
  "sourceFieldname" : "browser",
  "description" : "browser",
  "dataType" : "string",
  "hasIndex" : false,
  "unique" : false,
  "primarykey" : false,
  "namefield" : false,
  "nullable" : true,
  "custom" : false,
  "createable" : true,
  "updateable" : true,
  "audit" : false,
  "customizable" : false,
  "fieldLength" : 2147483647,
  "precision" : 0,
  "fieldOrder" : 0,
  "fieldProperties" : {
    "autoGenerated" : "false"
  },
  "etag" : "abe3ce3e-86d1-495a-a82c-06ff9464ff79",
  "isExtended" : false
}, {
  "name" : "component",
  "sourceFieldname" : "component",
  "description" : "component",
  "dataType" : "string",
  "hasIndex" : false,
  "unique" : false,
  "primarykey" : false,
  "namefield" : false,
  "nullable" : true,
  "custom" : false,
  "createable" : true,
  "updateable" : true,
  "audit" : false,
  "customizable" : false,
  "fieldLength" : 50,
  "precision" : 0,
  "fieldOrder" : 0,
  "fieldProperties" : {
    "autoGenerated" : "false"
  },
  "etag" : "3adf0842-8d31-4d14-aa5f-14f83f6f949c",
  "isExtended" : false
}, {
  "name" : "device",
  "sourceFieldname" : "device",
  "description" : "device",
  "dataType" : "string",
  "hasIndex" : false,
  "unique" : false,
  "primarykey" : false,
  "namefield" : false,
  "nullable" : true,
  "custom" : false,
  "createable" : true,
  "updateable" : true,
  "audit" : false,
  "customizable" : false,
  "fieldLength" : 50,
  "precision" : 0,
  "fieldOrder" : 0,
  "fieldProperties" : {
    "autoGenerated" : "false"
  },
  "etag" : "d0609434-c3f2-4320-93e2-b224e6d938a0",
  "isExtended" : false
}, {
  "name" : "id",
  "sourceFieldname" : "id",
  "description" : "id",
  "dataType" : "string",
  "hasIndex" : false,
  "unique" : false,
  "primarykey" : true,
  "namefield" : false,
  "nullable" : false,
  "custom" : false,
  "createable" : true,
  "updateable" : false,
  "audit" : false,
  "customizable" : false,
  "fieldLength" : 36,
  "precision" : 0,
  "fieldOrder" : 0,
  "fieldProperties" : {
    "autoGenerated" : "false"
  },
  "etag" : "549cfa80-e7a5-48a8-925b-e296aea1c7ee",
  "isExtended" : false
}, {
  "name" : "message",
  "sourceFieldname" : "message",
  "description" : "message",
  "dataType" : "string",
  "hasIndex" : false,
  "unique" : false,
  "primarykey" : false,
  "namefield" : false,
  "nullable" : true,
  "custom" : false,
  "createable" : true,
  "updateable" : true,
  "audit" : false,
  "customizable" : false,
  "fieldLength" : 2147483647,
  "precision" : 0,
  "fieldOrder" : 0,
  "fieldProperties" : {
    "autoGenerated" : "false"
  },
  "etag" : "640a061d-7d0e-4e69-8993-e20f62d2051b",
  "isExtended" : false
}, {
  "name" : "module",
  "sourceFieldname" : "module",
  "description" : "module",
  "dataType" : "string",
  "hasIndex" : false,
  "unique" : false,
  "primarykey" : false,
  "namefield" : false,
  "nullable" : true,
  "custom" : false,
  "createable" : true,
  "updateable" : true,
  "audit" : false,
  "customizable" : false,
  "fieldLength" : 50,
  "precision" : 0,
  "fieldOrder" : 0,
  "fieldProperties" : {
    "autoGenerated" : "false"
  },
  "etag" : "00088709-138b-43da-9fd1-7c3b5f3e3b08",
  "isExtended" : false
}, {
  "name" : "option_id",
  "sourceFieldname" : "option_id",
  "description" : "option_id",
  "dataType" : "number",
  "hasIndex" : false,
  "unique" : false,
  "primarykey" : false,
  "namefield" : false,
  "nullable" : true,
  "custom" : false,
  "createable" : true,
  "updateable" : true,
  "audit" : false,
  "customizable" : false,
  "fieldLength" : 10,
  "precision" : 0,
  "fieldOrder" : 0,
  "fieldProperties" : {
    "autoGenerated" : "false"
  },
  "etag" : "5a0fa123-4621-4486-bd6f-2588412eff4e",
  "isExtended" : false
}, {
  "name" : "platform",
  "sourceFieldname" : "platform",
  "description" : "platform",
  "dataType" : "string",
  "hasIndex" : false,
  "unique" : false,
  "primarykey" : false,
  "namefield" : false,
  "nullable" : true,
  "custom" : false,
  "createable" : true,
  "updateable" : true,
  "audit" : false,
  "customizable" : false,
  "fieldLength" : 50,
  "precision" : 0,
  "fieldOrder" : 0,
  "fieldProperties" : {
    "autoGenerated" : "false"
  },
  "etag" : "18ea3d9b-47c8-47bf-b430-c980b9002e82",
  "isExtended" : false
}, {
  "name" : "status",
  "sourceFieldname" : "status",
  "description" : "status",
  "dataType" : "string",
  "hasIndex" : false,
  "unique" : false,
  "primarykey" : false,
  "namefield" : false,
  "nullable" : true,
  "custom" : false,
  "createable" : true,
  "updateable" : true,
  "audit" : false,
  "customizable" : false,
  "fieldLength" : 20,
  "precision" : 0,
  "fieldOrder" : 0,
  "fieldProperties" : {
    "autoGenerated" : "false"
  },
  "etag" : "0ae83a35-d37c-416d-8ebd-c441a4cd15f7",
  "isExtended" : false
}, {
  "name" : "user_ip",
  "sourceFieldname" : "user_ip",
  "description" : "user_ip",
  "dataType" : "string",
  "hasIndex" : false,
  "unique" : false,
  "primarykey" : false,
  "namefield" : false,
  "nullable" : true,
  "custom" : false,
  "createable" : true,
  "updateable" : true,
  "audit" : false,
  "customizable" : false,
  "fieldLength" : 50,
  "precision" : 0,
  "fieldOrder" : 0,
  "fieldProperties" : {
    "autoGenerated" : "false"
  },
  "etag" : "393737f1-d122-4237-bfc8-dfb66839c910",
  "isExtended" : false
} ]