{
    "@class": "com.kony.gen.viz.model.container.KVizSegment2",
    "DNDConfig": null,
    "_data_": [
        {
            "imgChevronRight": {
                "@class": "com.viz.ide.model.segment.ImageSegmentData",
                "src": "",
                "type": "Image"
            },
            "lblItemName": {
                "@class": "com.viz.ide.model.segment.SimpleTextSegmentData",
                "text": "Today's Auction",
                "type": "Label"
            }
        },
        {
            "imgChevronRight": {
                "@class": "com.viz.ide.model.segment.ImageSegmentData",
                "src": "",
                "type": "Image"
            },
            "lblItemName": {
                "@class": "com.viz.ide.model.segment.SimpleTextSegmentData",
                "text": "Auction Calendar",
                "type": "Label"
            }
        }
    ],
    "_height_": {
        "type": "ref",
        "value": "preferred"
    },
    "_indicator_": "none",
    "_left_": {
        "type": "string",
        "value": "0"
    },
    "_margin_": [
        0,
        0,
        0,
        0
    ],
    "_orientation_": 2,
    "_padding_": [
        0,
        0,
        0,
        0
    ],
    "_top_": {
        "type": "string",
        "value": "0"
    },
    "_width_": {
        "type": "string",
        "value": "100%"
    },
    "autogrowmode": 1,
    "canUpdateUI": true,
    "containerweight": 100,
    "counter": "01",
    "focusedindex": null,
    "focuseditem": null,
    "generatedtemplate": null,
    "groupcells": false,
    "hasSections": false,
    "id": "segAuctionItems",
    "info": null,
    "ipad": {
        "psp": {
            "indicator": "rowselect"
        }
    },
    "iphone": {
        "psp": {
            "indicator": "rowselect"
        }
    },
    "iscustomlayout": false,
    "isvisible": true,
    "kuid": "b1f616c268c448cda773923507b0db2f",
    "masterdata": {},
    "name": "kony.ui.SegmentedUI2",
    "needpageindicator": true,
    "pageoffdotimage": "pageoffdot.png",
    "pageondotimage": "pageondot.png",
    "paginationconfig": {
        "position": "bottom"
    },
    "parent": "flxBody",
    "pf": "frmOpenAuctions",
    "retaincontentalignment": false,
    "retainflexpositionproperties": false,
    "retainselection": false,
    "rowTemplateId": "c338e217dc7d430fb10b9da866fa240e",
    "rowcounter": 1,
    "rowfocusskin": "s961e586fe794e498e31c111fe40ef67",
    "rowskin": "s2d1a440627e4c3eb337995bf3931fdd",
    "rowtemplate": "Flex0j5bca553a5e142",
    "screenlevelwidget": false,
    "seccounter": 0,
    "sectionHeaderTemplateId": null,
    "sectionheaderskin": "s394e25221a84c198a12829462d278f1",
    "selectedRows": null,
    "selectedState": false,
    "selectedindex": null,
    "selectedindices": null,
    "selecteditems": null,
    "selectedsectionindex": 0,
    "selectionbehavior": "default",
    "separatorrequired": false,
    "separatorthickness": 0,
    "showscrollbars": false,
    "viewtype": "tableview",
    "vizProps": {},
    "wType": "Segment",
    "widgetalignment": 5,
    "widgetdatamap": {
        "flxChevronright": "flxChevronright",
        "flxInsideItem": "flxInsideItem",
        "flxMenuBarItems": "flxMenuBarItems",
        "imgChevronRight": "imgChevronRight",
        "lblItemName": "lblItemName"
    }
}