{
    "DNDConfig": null,
    "_height_": {
        "type": "string",
        "value": "220dp"
    },
    "_left_": {
        "type": "string",
        "value": "0"
    },
    "_margin_": [
        0,
        0,
        0,
        0
    ],
    "_orientation_": 6,
    "_padding_": [
        0,
        0,
        0,
        0
    ],
    "_percent_": true,
    "_skin_": "sf147ba359c4473099bd75eecaeaf506",
    "_top_": {
        "type": "string",
        "value": "0"
    },
    "_width_": {
        "type": "string",
        "value": "100%"
    },
    "allboxes": [],
    "canUpdateUI": true,
    "children": [
        "lblComingSoon"
    ],
    "clipbounds": false,
    "containerweight": 100,
    "enablescrolling": true,
    "id": "flxHeading",
    "info": null,
    "iscustomlayout": false,
    "isvisible": true,
    "kuid": "f8bec8f636dc41288ab330d34ae0c5b8",
    "layouttype": 2,
    "name": "kony.ui.FlexContainer",
    "parent": "flxBody",
    "pf": "CopyfrmCominSoon",
    "retaincontentalignment": false,
    "retainflexpositionproperties": false,
    "retainflowhorizontalalignment": false,
    "snapgridsize": 10,
    "snaptogrid": true,
    "wType": "FlexContainer",
    "widgetalignment": 1
}